LICENSE
MANIFEST.in
README.md
setup.py
bmaquet_tap_github.egg-info/PKG-INFO
bmaquet_tap_github.egg-info/SOURCES.txt
bmaquet_tap_github.egg-info/dependency_links.txt
bmaquet_tap_github.egg-info/entry_points.txt
bmaquet_tap_github.egg-info/requires.txt
bmaquet_tap_github.egg-info/top_level.txt
tap_github/__init__.py
tap_github/schemas/assignees.json
tap_github/schemas/collaborators.json
tap_github/schemas/comments.json
tap_github/schemas/commit_comments.json
tap_github/schemas/commits.json
tap_github/schemas/events.json
tap_github/schemas/issue_events.json
tap_github/schemas/issue_labels.json
tap_github/schemas/issue_milestones.json
tap_github/schemas/issues.json
tap_github/schemas/project_cards.json
tap_github/schemas/project_columns.json
tap_github/schemas/projects.json
tap_github/schemas/pull_request_reviews.json
tap_github/schemas/pull_requests.json
tap_github/schemas/releases.json
tap_github/schemas/review_comments.json
tap_github/schemas/reviews.json
tap_github/schemas/stargazers.json
tap_github/schemas/team_members.json
tap_github/schemas/team_memberships.json
tap_github/schemas/teams.json