Metadata-Version: 2.1
Name: bmaquet-tap-github
Version: 1.0.2
Summary: Singer.io tap for extracting data from the GitHub API
Home-page: https://github.com/BenjMaq/bmaquet-tap-github
Author: Stitch
License: UNKNOWN
Platform: UNKNOWN
Classifier: Programming Language :: Python :: 3 :: Only
Provides-Extra: dev
License-File: LICENSE
